netcdf2dataframe/__init__.py
netcdf2dataframe/read_netcdf.py
netcdf2dataframe-0.1.0.dist-info/METADATA
netcdf2dataframe-0.1.0.dist-info/WHEEL
netcdf2dataframe-0.1.0.dist-info/RECORD
