Metadata-Version: 2.1
Name: netcdf2dataframe
Version: 0.1.0
Summary: Small utilities to transform netCDF files into (GeoDataFrames)
Home-page: https://github.com/tgrandje/french-cities/
Keywords: climatology,oceanography
Author: Thomas Grandjean
Author-email: thomas.grandjean@developpement-durable.gouv.fr
Requires-Python: >=3.10,<4.0
Classifier: Development Status :: 3 - Alpha
Classifier: Operating System :: OS Independent
Classifier: Programming Language :: Python :: 3
Classifier: Programming Language :: Python :: 3.10
Classifier: Programming Language :: Python :: 3.11
Classifier: Programming Language :: Python :: 3.12
Classifier: Programming Language :: Python :: 3.13
Classifier: Topic :: Scientific/Engineering
Requires-Dist: geopandas (>=1.0.1,<2.0.0)
Requires-Dist: importlib-metadata (>=8.6.1,<9.0.0)
Requires-Dist: netcdf4 (>=1.7.2,<2.0.0)
Requires-Dist: pandas (>=2.2.3,<3.0.0)
